wristband/py.typed
wristband/python_jwt/__init__.py
wristband/python_jwt/jwks_client.py
wristband/python_jwt/models.py
wristband/python_jwt/validator.py
wristband/python_jwt/utils/__init__.py
wristband/python_jwt/utils/cache.py
wristband/python_jwt/utils/crypto.py
wristband_python_jwt-0.1.0.dist-info/licenses/LICENSE
wristband_python_jwt-0.1.0.dist-info/METADATA
wristband_python_jwt-0.1.0.dist-info/WHEEL
wristband_python_jwt-0.1.0.dist-info/top_level.txt
wristband_python_jwt-0.1.0.dist-info/RECORD
