Metadata-Version: 2.4
Name: wristband-python-jwt
Version: 0.1.0
Summary: Framework-agnostic Python SDK for validating JWT access tokens issued by Wristband.
Author-email: Wristband <support@wristband.dev>
License-Expression: MIT
Project-URL: Homepage, https://wristband.dev
Project-URL: Repository, https://github.com/wristband-dev/python-jwt
Project-URL: Documentation, https://docs.wristband.dev
Keywords: api,auth,authentication,authorization,fastapi,flask,django,jwt,multi-tenant,multi-tenancy,oauth,oidc,sdk,secure,security,sso,validation,wristband
Classifier: Programming Language :: Python :: 3
Classifier: Programming Language :: Python :: 3.9
Classifier: Programming Language :: Python :: 3.10
Classifier: Programming Language :: Python :: 3.11
Classifier: Programming Language :: Python :: 3.12
Classifier: Programming Language :: Python :: 3.13
Classifier: Operating System :: OS Independent
Classifier: Intended Audience :: Developers
Classifier: Topic :: Software Development :: Libraries :: Python Modules
Classifier: Topic :: Security
Classifier: Development Status :: 4 - Beta
Classifier: Framework :: FastAPI
Classifier: Framework :: Flask
Classifier: Framework :: Django
Requires-Python: >=3.9
License-File: LICENSE
Requires-Dist: cryptography<45.0.0,>=41.0.0
Requires-Dist: httpx>=0.24.0
Provides-Extra: dev
Requires-Dist: setuptools>=61; extra == "dev"
Requires-Dist: pytest<9.0.0,>=8.2.0; extra == "dev"
Requires-Dist: pytest-cov<6.0.0,>=5.0.0; extra == "dev"
Requires-Dist: pytest-httpx>=0.21.0; extra == "dev"
Requires-Dist: mypy>=1.10.0; extra == "dev"
Requires-Dist: flake8<7.0.0,>=6.0.0; extra == "dev"
Requires-Dist: flake8-pyproject>=1.2.0; extra == "dev"
Requires-Dist: pip-audit>=2.0.0; extra == "dev"
Requires-Dist: bandit>=1.7.0; extra == "dev"
Requires-Dist: build>=0.10.0; extra == "dev"
Requires-Dist: twine>=4.0.0; extra == "dev"
Requires-Dist: black>=23.0.0; extra == "dev"
Requires-Dist: isort>=5.12.0; extra == "dev"
Dynamic: license-file
